shaikh/__init__.py
shaikh/a1.py
shaikh/a2.py
shaikh-0.0.1.dist-info/LICENSE.txt
shaikh-0.0.1.dist-info/METADATA
shaikh-0.0.1.dist-info/WHEEL
shaikh-0.0.1.dist-info/top_level.txt
shaikh-0.0.1.dist-info/RECORD
